{
  "heroes": [
    {
      "id": 33,
      "name": "Бобрик",
      "description": "спать",
      "element": "earth"
    },
    {
      "id": 75,
      "name": "ветер",
      "description": "дуть",
      "element": "wind"
    },
    {
      "id": 92,
      "name": "огонь",
      "description": "гореть",
      "element": "fire"
    },
    {
      "id": 82,
      "name": "Denis",
      "description": "Puki",
      "element": "fire"
    }
  ],
  "filters": [
    {
      "name": "all",
      "label": "Все",
      "className": "btn-outline-dark",
      "id": "1"
    },
    {
      "name": "fire",
      "label": "Огонь",
      "className": "btn-danger",
      "id": "2"
    },
    {
      "name": "water",
      "label": "Вода",
      "className": "btn-primary",
      "id": "3"
    },
    {
      "name": "wind",
      "label": "Ветер",
      "className": "btn-success",
      "id": "4"
    },
    {
      "name": "earth",
      "label": "Земля",
      "className": "btn-secondary",
      "id": "5"
    }
  ]
}